{
  "AcLogHost": "127.0.0.1",
  "AcLogPort": 1100,
  "WfviewHost": "127.0.0.1",
  "WfviewPort": 4533,
  "WfviewPath": "C:\\Program Files\\wfview\\wfview.exe",
  "AcLogPath": "C:\\N3FJP Software\\ACLog\\ACLog.exe",
  "WfviewServerHost": "100.x.y.z",
  "WfviewServerPath": "C:\\Program Files\\wfview\\wfview.exe",
  "AutoConnectOnStartup": true,
  "AutoStartStationOnStartup": false,
  "AutoLaunchWfview": false,
  "AutoLaunchAcLog": false,
  "LaunchWfviewServerDuringStartStation": false,
  "SyncRfPowerToAcLog": false,
  "RadioMaxPowerWatts": 100.0,
  "ShellyEnabled": false,
  "ShellyHost": "shellyplugusg4-xxxxxxxxxxxx.local",
  "ShellyPort": 80,
  "ShellySwitchId": 0,
  "StationOffPowerThresholdWatts": 5.0,
  "StationPowerOnDelaySeconds": 8,
  "WfviewServerAudioWaitSeconds": 45,
  "WfviewServerSettleDelaySeconds": 8,
  "AcLogLaunchDelaySeconds": 2,
  "ShowEventLog": true,
  "ShowAcLogStatus": true,
  "ShowWfviewStatus": true,
  "ShowRadioFrequency": true,
  "ShowModeAndRfPower": true,
  "ShowLastRequestedFrequency": true,
  "ShowLastConfirmedFrequency": true,
  "ShowTuneResult": true,
  "ExpandPowerPanel": true,
  "DarkModeEnabled": false,
  "MainWindowLeft": null,
  "MainWindowTop": null,
  "MainWindowWidth": null,
  "MainWindowHeight": null,
  "MainWindowMaximized": false
}
